odoo/addons/stock_picking_carrier_from_rule/README.rst
odoo/addons/stock_picking_carrier_from_rule/__init__.py
odoo/addons/stock_picking_carrier_from_rule/__manifest__.py
odoo/addons/stock_picking_carrier_from_rule/i18n/es.po
odoo/addons/stock_picking_carrier_from_rule/i18n/it.po
odoo/addons/stock_picking_carrier_from_rule/i18n/stock_picking_carrier_from_rule.pot
odoo/addons/stock_picking_carrier_from_rule/models/__init__.py
odoo/addons/stock_picking_carrier_from_rule/models/stock_move.py
odoo/addons/stock_picking_carrier_from_rule/readme/CONTRIBUTORS.rst
odoo/addons/stock_picking_carrier_from_rule/readme/CREDITS.rst
odoo/addons/stock_picking_carrier_from_rule/readme/DESCRIPTION.rst
odoo/addons/stock_picking_carrier_from_rule/readme/ROADMAP.rst
odoo/addons/stock_picking_carrier_from_rule/static/description/icon.png
odoo/addons/stock_picking_carrier_from_rule/static/description/index.html
odoo14_addon_stock_picking_carrier_from_rule-14.0.1.0.1.dev9.dist-info/METADATA
odoo14_addon_stock_picking_carrier_from_rule-14.0.1.0.1.dev9.dist-info/WHEEL
odoo14_addon_stock_picking_carrier_from_rule-14.0.1.0.1.dev9.dist-info/top_level.txt
odoo14_addon_stock_picking_carrier_from_rule-14.0.1.0.1.dev9.dist-info/RECORD
